<?xml version="1.0" encoding="utf-8"?>
<odoo>
	<record id="wizard_altas_y_bajas_form_view" model="ir.ui.view">
        <field name="name">altas.y.bajas.form.view</field>
        <field name="model">altas.y.bajas</field>
        <field name="arch" type="xml">
	        <form string="Altas Y Bajas">
	            <group >
	                <group>
	                    <field name="start_date"/>
	                    <field name="tipo" required="1"/>
	                </group>
	                <group>
	                    <field name="end_date"/>
	                </group>
	            </group>
	            <footer>
	                <button name="print_altas_y_bajas_report" string="Imprimir" type="object" default_focus="1" class="oe_highlight"/>
	                <button string="Cancelar" class="btn btn-default" special="cancel" />
	            </footer>
	        </form>
        </field>
    </record>
    
    <record id="action_wizard_altas_y_bajas" model="ir.actions.act_window">
        <field name="name">Altas y Bajas</field>
        <field name="res_model">altas.y.bajas</field>
        <field name="type">ir.actions.act_window</field>
        <field name="view_mode">form</field>
        <field name="view_id" ref="wizard_altas_y_bajas_form_view"/>
        <field name="target">new</field>
    </record>

    <menuitem id="menu_action_wizard_altas_y_bajas"
            name="Altas y Bajas"
            action="action_wizard_altas_y_bajas"
            parent="menu_main_reportes"
            sequence="10"/>

</odoo>
