<?xml version="1.0" encoding="utf-8"?>
<odoo>
  <data>
    <record model="ir.ui.view" id="sod_set_groups_formview_inh">
      <field name="name">Set Groups</field>
      <field name="model">set.groups.user</field>
      <field name="inherit_id" ref="grcbit_base.grcbit_base_set_groups_formview_inh"/>
      <field name="arch" type="xml">
        <xpath expr="//field[@name='guest_check']" position="after">
          <field name="dash_admin_check"/>
        </xpath>
      </field>
    </record>
  </data>
</odoo>
